{
  "id":"11741ebf-1dd7-40c2-a777-c89dc0d88c9c",
  "person":{
    "name":{
      "firstName":"Aastha",
      "lastName":"Chande"
    },
    "education":[
      {
        "startYear":2016,
        "endYear":2018,
        "university":{
          "name":"San Jose State University",
          "city":"San Jose",
          "state":"CA"
        },
        "degree":"Associate"
      }
    ],
    "address":{
      "zipCode":"95116",
      "stateShortName":"CA",
      "stateFullName":"California",
      "city":"San Jose",
      "street":"McKee Road",
      "house":"2367"
    },
    "phoneNumber":"3606528594",
    "gender":1,
    "origin":1
  },
  "email":"bertramhoehe@yahoo.com",
  "passd":"06ad971b32"
}