{
  "id":"a1a6d6fd-1035-4290-8c8a-264e9038aab9",
  "person":{
    "name":{
      "firstName":"Krithika",
      "lastName":"Lal"
    },
    "education":[
      {
        "startYear":2016,
        "endYear":2018,
        "university":{
          "name":"University of Kentucky",
          "city":"Lexington",
          "state":"KY"
        },
        "degree":"Associate"
      }
    ],
    "address":{
      "zipCode":"40516",
      "stateShortName":"KY",
      "stateFullName":"Kentucky",
      "city":"Lexington",
      "street":"Johnston Road",
      "house":"650"
    },
    "phoneNumber":"3306565190",
    "gender":1,
    "origin":1
  },
  "email":"ch.emilie540@yahoo.com",
  "passd":"c713215ba1"
}