{
  "id":"b2b5ce32-485f-431f-a0c8-eb845d69897d",
  "person":{
    "name":{
      "firstName":"Mahesh",
      "lastName":"Kumar"
    },
    "education":[
      {
        "startYear":2016,
        "endYear":2018,
        "university":{
          "name":"Penn State",
          "city":"State College",
          "state":"PA"
        },
        "degree":"Associate"
      }
    ],
    "address":{
      "zipCode":"16801",
      "stateShortName":"PA",
      "stateFullName":"Pennsylvania",
      "city":"State College",
      "street":"Decibel Road",
      "house":"521"
    },
    "phoneNumber":"4213785837",
    "gender":0,
    "origin":1
  },
  "email":"caseylucine@yahoo.com",
  "passd":"00b2029242"
}