{
  "id":"b731b38e-abfa-4040-9589-9f7bd1adb4bd",
  "person":{
    "name":{
      "firstName":"Aishwarya",
      "lastName":"Kumar"
    },
    "education":[
      {
        "startYear":2014,
        "endYear":2018,
        "university":{
          "name":"Western Governors University",
          "city":"Salt Lake City",
          "state":"UT"
        },
        "degree":"Bachelor"
      }
    ],
    "address":{
      "zipCode":"84010",
      "stateShortName":"UT",
      "stateFullName":"Utah",
      "city":"Bountiful",
      "street":"South 950 East",
      "house":"3080"
    },
    "phoneNumber":"4142126142",
    "gender":1,
    "origin":1
  },
  "email":"sanchezcelestyn@yahoo.com",
  "passd":"cad47d5460"
}