{
  "id":"c4e1a870-60f3-49f7-9b47-83cbba80261c",
  "person":{
    "name":{
      "firstName":"Caroline",
      "lastName":"Davis"
    },
    "education":[
      {
        "startYear":2016,
        "endYear":2018,
        "university":{
          "name":"Miami Dade College",
          "city":"Miami",
          "state":"FL"
        },
        "degree":"Master"
      },
      {
        "startYear":2014,
        "endYear":2016,
        "university":{
          "name":"Miami Dade College",
          "city":"Miami",
          "state":"FL"
        },
        "degree":"Bachelor"
      },
      {
        "startYear":2012,
        "endYear":2014,
        "university":{
          "name":"Miami Dade College",
          "city":"Miami",
          "state":"FL"
        },
        "degree":"Associate"
      }
    ],
    "address":{
      "zipCode":"33139",
      "stateShortName":"FL",
      "stateFullName":"Florida",
      "city":"Miami Beach",
      "street":"North Hibiscus Drive",
      "house":"429-437"
    },
    "phoneNumber":"2546909893",
    "gender":1,
    "origin":0
  },
  "email":"filosaariella@yahoo.com",
  "passd":"8ea7171640"
}