{
  "id":"d7f24f31-d0e0-4252-86c5-b80a8a63b687",
  "person":{
    "name":{
      "firstName":"Jay",
      "lastName":"Srivastav"
    },
    "education":[
      {
        "startYear":2014,
        "endYear":2018,
        "university":{
          "name":"California State Polytechnic University - Pomona",
          "city":"Pomona",
          "state":"CA"
        },
        "degree":"Bachelor"
      }
    ],
    "address":{
      "zipCode":"91766",
      "stateShortName":"CA",
      "stateFullName":"California",
      "city":"Pomona",
      "street":"East Mission Boulevard",
      "house":"4093-4099"
    },
    "phoneNumber":"2662741530",
    "gender":0,
    "origin":1
  },
  "email":"gottliebpincus@yahoo.com",
  "passd":"bd4d29e096"
}