{
  "id":"eae17196-13de-4ff9-853f-6314f97ba0cd",
  "person":{
    "name":{
      "firstName":"Katherine",
      "lastName":"Chandra"
    },
    "education":[
      {
        "startYear":2016,
        "endYear":2018,
        "university":{
          "name":"Texas Tech University",
          "city":"Lubbock",
          "state":"TX"
        },
        "degree":"Associate"
      }
    ],
    "address":{
      "zipCode":"79404",
      "stateShortName":"TX",
      "stateFullName":"Texas",
      "city":"Lubbock",
      "street":"Martin Luther King Junior Boulevard",
      "house":"5401"
    },
    "phoneNumber":"4472561710",
    "gender":1,
    "origin":1
  },
  "email":"schippersbaldwin@yahoo.com",
  "passd":"3a6e9c1834"
}